[{"buildOrder":3,"reportUrl":"https://assurdly.github.io/dettyfinance-admin-api/3","reportName":"Allure Report with history","data":{"duration":13480}},{"buildOrder":3,"reportUrl":"https://assurdly.github.io/dettyfinance-admin-api/3","reportName":"Allure Report with history","data":{"duration":13820}},{"buildOrder":2,"reportUrl":"https://assurdly.github.io/dettyfinance-admin-api/2","reportName":"Allure Report with history","data":{"duration":13748}},{"buildOrder":1,"reportUrl":"https://assurdly.github.io/dettyfinance-admin-api/1","reportName":"Allure Report with history","data":{"duration":9338}}]